webbot/__init__.py
webbot/webbot.py
webbot/drivers/chrome_linux
webbot/drivers/chrome_mac
webbot/drivers/chrome_windows.exe
mmwebbot-0.36.dist-info/LICENSE
mmwebbot-0.36.dist-info/METADATA
mmwebbot-0.36.dist-info/WHEEL
mmwebbot-0.36.dist-info/top_level.txt
mmwebbot-0.36.dist-info/RECORD
